Metadata-Version: 2.1
Name: amdgpu-fan-ctrl
Version: 0.0.2
Summary: AMD GPU fan control for Linux
Home-page: https://github.com/luismsgomes/amdgpu-fan-ctrl
Author: Luís Gomes
Author-email: luismsgomes@gmail.com
License: MIT
Platform: UNKNOWN
Classifier: Development Status :: 5 - Production/Stable
Classifier: License :: OSI Approved :: MIT License
Classifier: Programming Language :: Python :: 3
